Workbook

Sheet Overview
A2: FINCB9339 Homework 1 | Strategy replication
A3: Submission workbook | scored 2025-04-02 to 2025-12-01 | 168 sessions | initial capital $100,000
A6: Performance measure | B6: Model A | C6: Model B | D6: Model C | E6: SPY gross
A7: Cumulative return | B7: 0.035942128 | C7: 0.04474041 | D7: 0.11139267 | E7: 0.21962501
A8: Annualized geometric return | B8: 0.054394767 | C8: 0.067855749 | D8: 0.17165916 | E8: 0.34691281
A9: Annualized volatility | B9: 0.06649385 | C9: 0.072406091 | D9: 0.15499541 | E9: 0.21444632
A10: Sharpe, zero risk-free | B10: 0.82962629 | C10: 0.94237324 | D10: 1.096886 | E10: 1.4946744
A11: Maximum drawdown | B11: -0.05059485 | C11: -0.028361244 | D11: -0.04816985 | E11: -0.12052728
A12: Final equity ($) | B12: 103594.21 | C12: 104474.04 | D12: 111139.27 | E12: 121962.5
A13: Completed round trips | B13: 95 | C13: 135 | D13: 135
A14: Total transaction costs ($) | B14: 138.33 | C14: 201.42 | D14: 534.915
A15: Trade hit ratio | B15: 0.58947368 | C15: 0.42962963 | D15: 0.42962963
A16: Average trade net P&L ($) | B16: 37.833819 | C16: 33.141044 | D16: 82.513089
A17: Best day return | B17: 0.02324771 | C17: 0.037399471 | D17: 0.093220109 | E17: 0.10501945
A18: Worst day return | B18: -0.017482629 | C18: -0.014319607 | D18: -0.020114992 | E18: -0.058542848
A19: Annualized alpha vs SPY | B19: 0.098285538 | C19: 0.052262771 | D19: 0.1768759
A20: Beta vs SPY | B20: -0.1345298 | C20: 0.049826597 | D20: -0.021413485
A21: HAC alpha p-value | B21: 0.20912091 | C21: 0.47744231 | D21: 0.35271422
A24: Method and source
A25: Model A — 14 prior sessions; gap-adjusted Noise Area; opposite boundary exit.
A26: Model B — Model A entry; long stop max(upper,VWAP proxy), short stop min(lower,VWAP proxy).
A27: Model C — Model B plus min(4,2% / prior-14-day daily SPY volatility) sizing.
A28: Execution — 30-minute grid, observed price reference, daily close liquidation.
A29: Costs — $0.0035/share commission + $0.001/share slippage on each execution leg.
A30: Data limits — first interval open proxy; endpoint price-volume VWAP proxy.
A31: Half days — July 3 and November 28 liquidated at 13:00; stale prints excluded.
A32: Audit — Daily Results → Trade Log → Execution Log / Signal Inputs → source tabs.
A33: Validation — April Noise/Volatility show live formulas; sensitivities are fixed independent runs.
A34: Source SHA-256 — 102acfdcca2c4c23e82c78fabbdf0f9703281009704e156b5f9f508dc424ba88

Sheet Daily Results
A2: Baseline daily results | common scored dates
A3: Frozen Python backtest values. Three Excel SUMIFS columns reconcile each day to completed trade net P&L.
A6: Date | B6: A start $ | C6: A gross $ | D6: A costs $ | E6: A net $ | F6: A end $ | G6: A return | H6: B start $ | I6: B gross $ | J6: B costs $ | K6: B net $ | L6: B end $ | M6: B return | N6: C start $ | O6: C gross $ | P6: C costs $ | Q6: C net $ | R6: C end $ | S6: C return | T6: SPY return | U6: SPY equity $ | V6: A trade net $ | W6: B trade net $ | X6: C trade net $ | Y6: A Δ $ | Z6: B Δ $ | AA6: C Δ $
A7: 45749 | B7: 100000 | C7: 218.34 | D7: 1.62 | E7: 216.72 | F7: 100216.72 | G7: 0.0021672 | H7: 100000 | I7: -766.008 | J7: 3.24 | K7: -769.248 | L7: 99230.752 | M7: -0.00769248 | N7: 100000 | O7: -1285.1912 | P7: 5.436 | Q7: -1290.6272 | R7: 98709.373 | S7: -0.012906272 | T7: 0.0063282379 | U7: 100632.82 | V7: =SUMIFS('Trade Log'!$N$7:$N$371,'Trade Log'!$A$7:$A$371,"A",'Trade Log'!$C$7:$C$371,A7) -> 216.72 | W7: =SUMIFS('Trade Log'!$N$7:$N$371,'Trade Log'!$A$7:$A$371,"B",'Trade Log'!$C$7:$C$371,A7) -> -769.248 | X7: =SUMIFS('Trade Log'!$N$7:$N$371,'Trade Log'!$A$7:$A$371,"C",'Trade Log'!$C$7:$C$371,A7) -> -1290.6272 | Y7: =V7-E7 -> 1.4239276e-11 | Z7: =W7-K7 -> 7.5033313e-12 | AA7: =X7-Q7 -> 1.2505552e-11
A8: 45750 | B8: 100216.72 | C8: 1153.327 | D8: 1.665 | E8: 1151.662 | F8: 101368.38 | G8: 0.011491715 | H8: 99230.752 | I8: 146.4732 | J8: 4.941 | K8: 141.5322 | L8: 99372.284 | M8: 0.0014262937 | N8: 98709.373 | O8: 258.5292 | P8: 8.721 | Q8: 249.8082 | R8: 98959.181 | S8: 0.0025307445 | T8: -0.049280821 | U8: 95673.556 | V8: =SUMIFS('Trade Log'!$N$7:$N$371,'Trade Log'!$A$7:$A$371,"A",'Trade Log'!$C$7:$C$371,A8) -> 1151.662 | W8: =SUMIFS('Trade Log'!$N$7:$N$371,'Trade Log'!$A$7:$A$371,"B",'Trade Log'!$C$7:$C$371,A8) -> 141.5322 | X8: =SUMIFS('Trade Log'!$N$7:$N$371,'Trade Log'!$A$7:$A$371,"C",'Trade Log'!$C$7:$C$371,A8) -> 249.8082 | Y8: =V8-E8 -> -2.5011104e-12 | Z8: =W8-K8 -> -5.8548721e-12 | AA8: =X8-Q8 -> -1.0402346e-11
A9: 45751 | B9: 101368.38 | C9: 2095.8014 | D9: 1.746 | E9: 2094.0554 | F9: 103462.44 | G9: 0.020657875 | H9: 99372.284 | I9: 2063.3921 | J9: 1.719 | K9: 2061.6731 | L9: 101433.96 | M9: 0.020746963 | N9: 98959.181 | O9: 2473.9099 | P9: 2.061 | Q9: 2471.8489 | R9: 101431.03 | S9: 0.02497847 | T9: -0.058542848 | U9: 90072.553 | V9: =SUMIFS('Trade Log'!$N$7:$N$371,'Trade Log'!$A$7:$A$371,"A",'Trade Log'!$C$7:$C$371,A9) -> 2094.0554 | W9: =SUMIFS('Trade Log'!$N$7:$N$371,'Trade Log'!$A$7:$A$371,"B",'Trade Log'!$C$7:$C$371,A9) -> 2061.6731 | X9: =SUMIFS('Trade Log'!$N$7:$N$371,'Trade Log'!$A$7:$A$371,"C",'Trade Log'!$C$7:$C$371,A9) -> 2471.8489 | Y9: =V9-E9 -> -5.4569682e-12 | Z9: =W9-K9 -> -5.4569682e-12 | AA9: =X9-Q9 -> -6.3664629e-12
A10: 45754 | B10: 103462.44 | C10: -1008.504 | D10: 1.89 | E10: -1010.394 | F10: 102452.04 | G10: -0.0097658051 | H10: 101433.96 | I10: -823.4645 | J10: 1.845 | K10: -825.3095 | L10: 100608.65 | M10: -0.0081364222 | N10: 101431.03 | O10: -755.1772 | P10: 1.692 | Q10: -756.8692 | R10: 100674.16 | S10: -0.0074619098 | T10: -0.0017812589 | U10: 89912.111 | V10: =SUMIFS('Trade Log'!$N$7:$N$371,'Trade Log'!$A$7:$A$371,"A",'Trade Log'!$C$7:$C$371,A10) -> -1010.394 | W10: =SUMIFS('Trade Log'!$N$7:$N$371,'Trade Log'!$A$7:$A$371,"B",'Trade Log'!$C$7:$C$371,A10) -> -825.3095 | X10: =SUMIFS('Trade Log'!$N$7:$N$371,'Trade Log'!$A$7:$A$371,"C",'Trade Log'!$C$7:$C$371,A10) -> -756.8692 | Y10: =V10-E10 -> -7.1622708e-12 | Z10: =W10-K10 -> -4.4337867e-12 | AA10: =X10-Q10 -> -3.9790393e-12
A11: 45755 | B11: 102452.04 | C11: 153.5024 | D11: 1.773 | E11: 151.7294 | F11: 102603.77 | G11: 0.0014809797 | H11: 100608.65 | I11: 150.3856 | J11: 1.737 | K11: 148.6486 | L11: 100757.3 | M11: 0.0014774933 | N11: 100674.16 | O11: 137.1392 | P11: 1.584 | Q11: 135.5552 | R11: 100809.72 | S11: 0.0013464746 | T11: -0.01566293 | U11: 88503.824 | V11: =SUMIFS('Trade Log'!$N$7:$N$371,'Trade Log'!$A$7:$A$371,"A",'Trade Log'!$C$7:$C$371,A11) -> 151.7294 | W11: =SUMIFS('Trade Log'!$N$7:$N$371,'Trade Log'!$A$7:$A$371,"B",'Trade Log'!$C$7:$C$371,A11) -> 148.6486 | X11: =SUMIFS('Trade Log'!$N$7:$N$371,'Trade Log'!$A$7:$A$371,"C",'Trade Log'!$C$7:$C$371,A11) -> 135.5552 | Y11: =V11-E11 -> 5.968559e-13 | Z11: =W11-K11 -> 5.968559e-13 | AA11: =X11-Q11 -> 5.1159077e-13
A12: 45756 | B12: 102603.77 | C12: -1595.5936 | D12: 3.708 | E12: -1599.3016 | F12: 101004.47 | G12: -0.015587162 | H12: 100757.3 | I12: 3771.9056 | J12: 3.636 | K12: 3768.2696 | L12: 104525.57 | M12: 0.037399471 | N12: 100809.72 | O12: 3529.1592 | P12: 3.402 | Q12: 3525.7572 | R12: 104335.47 | S12: 0.034974379 | T12: 0.10501945 | U12: 97798.447 | V12: =SUMIFS('Trade Log'!$N$7:$N$371,'Trade Log'!$A$7:$A$371,"A",'Trade Log'!$C$7:$C$371,A12) -> -1599.3016 | W12: =SUMIFS('Trade Log'!$N$7:$N$371,'Trade Log'!$A$7:$A$371,"B",'Trade Log'!$C$7:$C$371,A12) -> 3768.2696 | X12: =SUMIFS('Trade Log'!$N$7:$N$371,'Trade Log'!$A$7:$A$371,"C",'Trade Log'!$C$7:$C$371,A12) -> 3525.7572 | Y12: =V12-E12 -> -1.7053026e-11 | Z12: =W12-K12 -> 0 | AA12: =X12-Q12 -> 0
A13: 45757 | B13: 101004.47 | C13: -148.9152 | D13: 1.728 | E13: -150.6432 | F13: 100853.83 | G13: -0.0014914508 | H13: 104525.57 | I13: -76.7844 | J13: 1.782 | K13: -78.5664 | L13: 104447 | M13: -0.0007516477 | N13: 104335.47 | O13: -41.1068 | P13: 0.954 | Q13: -42.0608 | R13: 104293.41 | S13: -0.0004031304 | T13: -0.043819119 | U13: 93513.005 | V13: =SUMIFS('Trade Log'!$N$7:$N$371,'Trade Log'!$A$7:$A$371,"A",'Trade Log'!$C$7:$C$371,A13) -> -150.6432 | W13: =SUMIFS('Trade Log'!$N$7:$N$371,'Trade Log'!$A$7:$A$371,"B",'Trade Log'!$C$7:$C$371,A13) -> -78.5664 | X13: =SUMIFS('Trade Log'!$N$7:$N$371,'Trade Log'!$A$7:$A$371,"C",'Trade Log'!$C$7:$C$371,A13) -> -42.0608 | Y13: =V13-E13 -> 1.1453949e-11 | Z13: =W13-K13 -> 5.9117156e-12 | AA13: =X13-Q13 -> 3.1619152e-12
A14: 45758 | B14: 100853.83 | C14: -1759.7161 | D14: 3.474 | E14: -1763.1901 | F14: 99090.638 | G14: -0.017482629 | H14: 104447 | I14: -1488.44 | J14: 7.2 | K14: -1495.64 | L14: 102951.36 | M14: -0.014319607 | N14: 104293.41 | O14: -759.1044 | P14: 3.672 | Q14: -762.7764 | R14: 103530.64 | S14: -0.0073137544 | T14: 0.017843034 | U14: 95181.561 | V14: =SUMIFS('Trade Log'!$N$7:$N$371,'Trade Log'!$A$7:$A$371,"A",'Trade Log'!$C$7:$C$371,A14) -> -1763.1901 | W14: =SUMIFS('Trade Log'!$N$7:$N$371,'Trade Log'!$A$7:$A$371,"B",'Trade Log'!$C$7:$C$371,A14) -> -1495.64 | X14: =SUMIFS('Trade Log'!$N$7:$N$371,'Trade Log'!$A$7:$A$371,"C",'Trade Log'!$C$7:$C$371,A14) -> -762.7764 | Y14: =V14-E14 -> -2.5011104e-12 | Z14: =W14-K14 -> -3.6834535e-11 | AA14: =X14-Q14 -> -1.8872015e-11
A15: 45761 | B15: 99090.638 | C15: 0 | D15: 0 | E15: 0 | F15: 99090.638 | G15: 0 | H15: 102951.36 | I15: 0 | J15: 0 | K15: 0 | L15: 102951.36 | M15: 0 | N15: 103530.64 | O15: 0 | P15: 0 | Q15: 0 | R15: 103530.64 | S15: 0 | T15: 0.0097013716 | U15: 96104.952 | V15: =SUMIFS('Trade Log'!$N$7:$N$371,'Trade Log'!$A$7:$A$371,"A",'Trade Log'!$C$7:$C$371,A15) -> 0 | W15: =SUMIFS('Trade Log'!$N$7:$N$371,'Trade Log'!$A$7:$A$371,"B",'Trade Log'!$C$7:$C$371,A15) -> 0 | X15: =SUMIFS('Trade Log'!$N$7:$N$371,'Trade Log'!$A$7:$A$371,"C",'Trade Log'!$C$7:$C$371,A15) -> 0 | Y15: =V15-E15 -> 0 | Z15: =W15-K15 -> 0 | AA15: =X15-Q15 -> 0
A16: 45762 | B16: 99090.638 | C16: 0 | D16: 0 | E16: 0 | F16: 99090.638 | G16: 0 | H16: 102951.36 | I16: 0 | J16: 0 | K16: 0 | L16: 102951.36 | M16: 0 | N16: 103530.64 | O16: 0 | P16: 0 | Q16: 0 | R16: 103530.64 | S16: 0 | T16: -0.0028008874 | U16: 95835.773 | V16: =SUMIFS('Trade Log'!$N$7:$N$371,'Trade Log'!$A$7:$A$371,"A",'Trade Log'!$C$7:$C$371,A16) -> 0 | W16: =SUMIFS('Trade Log'!$N$7:$N$371,'Trade Log'!$A$7:$A$371,"B",'Trade Log'!$C$7:$C$371,A16) -> 0 | X16: =SUMIFS('Trade Log'!$N$7:$N$371,'Trade Log'!$A$7:$A$371,"C",'Trade Log'!$C$7:$C$371,A16) -> 0 | Y16: =V16-E16 -> 0 | Z16: =W16-K16 -> 0 | AA16: =X16-Q16 -> 0
A17: 45763 | B17: 99090.638 | C17: 0 | D17: 0 | E17: 0 | F17: 99090.638 | G17: 0 | H17: 102951.36 | I17: 0 | J17: 0 | K17: 0 | L17: 102951.36 | M17: 0 | N17: 103530.64 | O17: 0 | P17: 0 | Q17: 0 | R17: 103530.64 | S17: 0 | T17: -0.022227959 | U17: 93705.539 | V17: =SUMIFS('Trade Log'!$N$7:$N$371,'Trade Log'!$A$7:$A$371,"A",'Trade Log'!$C$7:$C$371,A17) -> 0 | W17: =SUMIFS('Trade Log'!$N$7:$N$371,'Trade Log'!$A$7:$A$371,"B",'Trade Log'!$C$7:$C$371,A17) -> 0 | X17: =SUMIFS('Trade Log'!$N$7:$N$371,'Trade Log'!$A$7:$A$371,"C",'Trade Log'!$C$7:$C$371,A17) -> 0 | Y17: =V17-E17 -> 0 | Z17: =W17-K17 -> 0 | AA17: =X17-Q17 -> 0
A18: 45764 | B18: 99090.638 | C18: 0 | D18: 0 | E18: 0 | F18: 99090.638 | G18: 0 | H18: 102951.36 | I18: 0 | J18: 0 | K18: 0 | L18: 102951.36 | M18: 0 | N18: 103530.64 | O18: 0 | P18: 0 | Q18: 0 | R18: 103530.64 | S18: 0 | T18: 0.0014267369 | U18: 93839.233 | V18: =SUMIFS('Trade Log'!$N$7:$N$371,'Trade Log'!$A$7:$A$371,"A",'Trade Log'!$C$7:$C$371,A18) -> 0 | W18: =SUMIFS('Trade Log'!$N$7:$N$371,'Trade Log'!$A$7:$A$371,"B",'Trade Log'!$C$7:$C$371,A18) -> 0 | X18: =SUMIFS('Trade Log'!$N$7:$N$371,'Trade Log'!$A$7:$A$371,"C",'Trade Log'!$C$7:$C$371,A18) -> 0 | Y18: =V18-E18 -> 0 | Z18: =W18-K18 -> 0 | AA18: =X18-Q18 -> 0
... A174: 45992 | B174: 103686.02 | C174: -90.44 | D174: 1.368 | E174: -91.808 | F174: 103594.21 | G174: -0.0008854424 | H174: 104789.83 | I174: -314.415 | J174: 1.377 | K174: -315.792 | L174: 104474.04 | M174: -0.0030135748 | N174: 111793.56 | O174: -651.435 | P174: 2.853 | Q174: -654.288 | R174: 111139.27 | S174: -0.0058526451 | T174: -0.0045654751 | U174: 121962.5 | V174: =SUMIFS('Trade Log'!$N$7:$N$371,'Trade Log'!$A$7:$A$371,"A",'Trade Log'!$C$7:$C$371,A174) -> -91.808 | W174: =SUMIFS('Trade Log'!$N$7:$N$371,'Trade Log'!$A$7:$A$371,"B",'Trade Log'!$C$7:$C$371,A174) -> -315.792 | X174: =SUMIFS('Trade Log'!$N$7:$N$371,'Trade Log'!$A$7:$A$371,"C",'Trade Log'!$C$7:$C$371,A174) -> -654.288 | Y174: =V174-E174 -> -4.1353587e-12 | Z174: =W174-K174 -> -9.777068e-12 | AA174: =X174-Q174 -> -2.012257e-11

Sheet Trade Log
A2: Completed trade ledger | Models A, B, C
A3: Entry/exit prices and signal levels are frozen inputs; Excel formulas independently recalculate gross, cost, and net P&L.
A6: Model | B6: Trade ID | C6: Date | D6: Entry time | E6: Exit time | F6: Direction | G6: Shares | H6: Entry price $ | I6: Exit price $ | J6: Gross P&L $ | K6: Commission $ | L6: Slippage $ | M6: Total costs $ | N6: Net P&L $ | O6: Entry upper $ | P6: Entry lower $ | Q6: Entry VWAP $ | R6: Exit upper $ | S6: Exit lower $ | T6: Exit VWAP $ | U6: Exit reason
A7: A | B7: 1 | C7: 45749 | D7: 45749.479 | E7: 45749.667 | F7: 1 | G7: 180 | H7: 560.0867 | I7: 561.2997 | J7: =F7*G7*(I7-H7) -> 218.34 | K7: =2*G7*'Method Notes'!$B$8 -> 1.26 | L7: =2*G7*'Method Notes'!$B$9 -> 0.36 | M7: =K7+L7 -> 1.62 | N7: =J7-M7 -> 216.72 | O7: 559.54864 | P7: 553.61247 | Q7: 557.43009 | R7: 561.22147 | S7: 551.94679 | T7: 559.69858 | U7: session_close
A8: A | B8: 2 | C8: 45750 | D8: 45750.438 | E8: 45750.667 | F8: -1 | G8: 185 | H8: 539.8726 | I8: 533.6384 | J8: =F8*G8*(I8-H8) -> 1153.327 | K8: =2*G8*'Method Notes'!$B$8 -> 1.295 | L8: =2*G8*'Method Notes'!$B$9 -> 0.37 | M8: =K8+L8 -> 1.665 | N8: =J8-M8 -> 1151.662 | O8: 562.42341 | P8: 539.95765 | Q8: 540.57172 | R8: 564.95843 | S8: 537.51413 | T8: 537.86789 | U8: session_close
A9: A | B9: 3 | C9: 45751 | D9: 45751.438 | E9: 45751.667 | F9: -1 | G9: 194 | H9: 513.2007 | I9: 502.3976 | J9: =F9*G9*(I9-H9) -> 2095.8014 | K9: =2*G9*'Method Notes'!$B$8 -> 1.358 | L9: =2*G9*'Method Notes'!$B$9 -> 0.388 | M9: =K9+L9 -> 1.746 | N9: =J9-M9 -> 2094.0554 | O9: 534.78861 | P9: 518.85584 | Q9: 517.50886 | R9: 537.23451 | S9: 516.47255 | T9: 509.55478 | U9: session_close
A10: A | B10: 4 | C10: 45754 | D10: 45754.583 | E10: 45754.667 | F10: 1 | G10: 210 | H10: 506.3052 | I10: 501.5028 | J10: =F10*G10*(I10-H10) -> -1008.504 | K10: =2*G10*'Method Notes'!$B$8 -> 1.47 | L10: =2*G10*'Method Notes'!$B$9 -> 0.42 | M10: =K10+L10 -> 1.89 | N10: =J10-M10 -> -1010.394 | O10: 505.09718 | P10: 489.97167 | Q10: 496.59524 | R10: 506.88636 | S10: 488.21731 | T10: 497.44856 | U10: session_close
A11: A | B11: 5 | C11: 45755 | D11: 45755.646 | E11: 45755.667 | F11: -1 | G11: 197 | H11: 494.4271 | I11: 493.6479 | J11: =F11*G11*(I11-H11) -> 153.5024 | K11: =2*G11*'Method Notes'!$B$8 -> 1.379 | L11: =2*G11*'Method Notes'!$B$9 -> 0.394 | M11: =K11+L11 -> 1.773 | N11: =J11-M11 -> 151.7294 | O11: 524.08277 | P11: 497.61978 | Q11: 507.39754 | R11: 525.35521 | S11: 496.39274 | T11: 504.2758 | U11: session_close
A12: A | B12: 6 | C12: 45756 | D12: 45756.458 | E12: 45756.562 | F12: -1 | G12: 206 | H12: 490.317 | I12: 521.7765 | J12: =F12*G12*(I12-H12) -> -6480.657 | K12: =2*G12*'Method Notes'!$B$8 -> 1.442 | L12: =2*G12*'Method Notes'!$B$9 -> 0.412 | M12: =K12+L12 -> 1.854 | N12: =J12-M12 -> -6482.511 | O12: 500.56818 | P12: 490.44998 | Q12: 495.30708 | R12: 502.47451 | S12: 488.55783 | T12: 506.47917 | U12: breakout_or_reverse
A13: A | B13: 7 | C13: 45756 | D13: 45756.562 | E13: 45756.667 | F13: 1 | G13: 206 | H13: 521.7765 | I13: 545.4904 | J13: =F13*G13*(I13-H13) -> 4885.0634 | K13: =2*G13*'Method Notes'!$B$8 -> 1.442 | L13: =2*G13*'Method Notes'!$B$9 -> 0.412 | M13: =K13+L13 -> 1.854 | N13: =J13-M13 -> 4883.2094 | O13: 502.47451 | P13: 488.55783 | Q13: 506.47917 | R13: 504.02788 | S13: 487.01601 | T13: 523.88149 | U13: session_close
A14: A | B14: 8 | C14: 45757 | D14: 45757.479 | E14: 45757.667 | F14: -1 | G14: 192 | H14: 520.812 | I14: 521.5876 | J14: =F14*G14*(I14-H14) -> -148.9152 | K14: =2*G14*'Method Notes'!$B$8 -> 1.344 | L14: =2*G14*'Method Notes'!$B$9 -> 0.384 | M14: =K14+L14 -> 1.728 | N14: =J14-M14 -> -150.6432 | O14: 548.48381 | P14: 523.00038 | Q14: 524.32108 | R14: 556.51294 | S14: 515.2598 | T14: 519.65236 | U14: session_close
A15: A | B15: 9 | C15: 45758 | D15: 45758.438 | E15: 45758.542 | F15: -1 | G15: 193 | H15: 517.5607 | I15: 528.7863 | J15: =F15*G15*(I15-H15) -> -2166.5408 | K15: =2*G15*'Method Notes'!$B$8 -> 1.351 | L15: =2*G15*'Method Notes'!$B$9 -> 0.386 | M15: =K15+L15 -> 1.737 | N15: =J15-M15 -> -2168.2778 | O15: 523.82765 | P15: 519.90785 | Q15: 519.99487 | R15: 526.66128 | S15: 517.07726 | T15: 521.7902 | U15: breakout_or_reverse
A16: A | B16: 10 | C16: 45758 | D16: 45758.542 | E16: 45758.667 | F16: 1 | G16: 193 | H16: 528.7863 | I16: 530.8942 | J16: =F16*G16*(I16-H16) -> 406.8247 | K16: =2*G16*'Method Notes'!$B$8 -> 1.351 | L16: =2*G16*'Method Notes'!$B$9 -> 0.386 | M16: =K16+L16 -> 1.737 | N16: =J16-M16 -> 405.0877 | O16: 526.66128 | P16: 517.07726 | Q16: 521.7902 | R16: 532.73258 | S16: 511.01246 | T16: 525.91876 | U16: session_close
A17: A | B17: 11 | C17: 45768 | D17: 45768.479 | E17: 45768.667 | F17: -1 | G17: 192 | H17: 510.1432 | I17: 510.9486 | J17: =F17*G17*(I17-H17) -> -154.6368 | K17: =2*G17*'Method Notes'!$B$8 -> 1.344 | L17: =2*G17*'Method Notes'!$B$9 -> 0.384 | M17: =K17+L17 -> 1.728 | N17: =J17-M17 -> -156.3648 | O17: 526.91823 | P17: 510.98743 | Q17: 512.44077 | R17: 534.43047 | S17: 503.60391 | T17: 509.66152 | U17: session_close
A18: A | B18: 12 | C18: 45769 | D18: 45769.5 | E18: 45769.667 | F18: 1 | G18: 190 | H18: 523.2083 | I18: 524.2423 | J18: =F18*G18*(I18-H18) -> 196.46 | K18: =2*G18*'Method Notes'!$B$8 -> 1.33 | L18: =2*G18*'Method Notes'!$B$9 -> 0.38 | M18: =K18+L18 -> 1.71 | N18: =J18-M18 -> 194.75 | O18: 523.15122 | P18: 506.80471 | Q18: 521.04228 | R18: 529.47202 | S18: 500.58129 | T18: 522.20381 | U18: session_close
... A371: C | B371: 135 | C371: 45992 | D371: 45992.438 | E371: 45992.458 | F371: -1 | G371: 317 | H371: 679.675 | I371: 681.73 | J371: =F371*G371*(I371-H371) -> -651.435 | K371: =2*G371*'Method Notes'!$B$8 -> 2.219 | L371: =2*G371*'Method Notes'!$B$9 -> 0.634 | M371: =K371+L371 -> 2.853 | N371: =J371-M371 -> -654.288 | O371: 684.12088 | P371: 680.82109 | Q371: 680.8339 | R371: 685.48424 | S371: 679.4614 | T371: 681.04455 | U371: stop_or_reverse

Sheet Execution Log
A2: Every execution leg | Models A, B, C
A3: A same-timestamp reversal appears as separate exit and entry legs. Event P&L and costs are frozen baseline values.
A6: Model | B6: Trade ID | C6: Date | D6: Execution time | E6: Signal time | F6: Action | G6: Side | H6: Direction | I6: Shares | J6: Price $ | K6: Upper $ | L6: Lower $ | M6: Noise σ | N6: VWAP proxy $ | O6: Long stop $ | P6: Short stop $ | Q6: Leverage | R6: Gross P&L $ | S6: Commission $ | T6: Slippage $ | U6: Net P&L $ | V6: Reason | W6: Source timestamp
A7: A | B7: 1 | C7: 45749 | D7: 45749.479 | E7: 45749.479 | F7: ENTRY | G7: BUY | H7: 1 | I7: 180 | J7: 560.0867 | K7: 559.54864 | L7: 553.61247 | M7: 0.0031892078 | N7: 557.43009 | O7: 559.54864 | P7: 553.61247 | Q7: 1 | R7: 0 | S7: 0.63 | T7: 0.18 | U7: -0.81 | V7: breakout_or_reverse | W7: 45749.458
A8: A | B8: 1 | C8: 45749 | D8: 45749.667 | E8: 45749.667 | F8: EXIT | G8: SELL | H8: 1 | I8: 180 | J8: 561.2997 | K8: 561.22147 | L8: 551.94679 | M8: 0.0061883457 | N8: 559.69858 | O8: 561.22147 | P8: 551.94679 | Q8: 1 | R8: 218.34 | S8: 0.63 | T8: 0.18 | U8: 217.53 | V8: session_close | W8: 45749.646
A9: A | B9: 2 | C9: 45750 | D9: 45750.438 | E9: 45750.438 | F9: ENTRY | G9: SELL | H9: -1 | I9: 185 | J9: 539.8726 | K9: 562.42341 | L9: 539.95765 | M9: 0.0020023358 | N9: 540.57172 | O9: 562.42341 | P9: 539.95765 | Q9: 1 | R9: 0 | S9: 0.6475 | T9: 0.185 | U9: -0.8325 | V9: breakout_or_reverse | W9: 45750.417
A10: A | B10: 2 | C10: 45750 | D10: 45750.667 | E10: 45750.667 | F10: EXIT | G10: BUY | H10: -1 | I10: 185 | J10: 533.6384 | K10: 564.95843 | L10: 537.51413 | M10: 0.0065186733 | N10: 537.86789 | O10: 564.95843 | P10: 537.51413 | Q10: 1 | R10: 1153.327 | S10: 0.6475 | T10: 0.185 | U10: 1152.4945 | V10: session_close | W10: 45750.646
A11: A | B11: 3 | C11: 45751 | D11: 45751.438 | E11: 45751.438 | F11: ENTRY | G11: SELL | H11: -1 | I11: 194 | J11: 513.2007 | K11: 534.78861 | L11: 518.85584 | M11: 0.0021557865 | N11: 517.50886 | O11: 534.78861 | P11: 517.50886 | Q11: 1 | R11: 0 | S11: 0.679 | T11: 0.194 | U11: -0.873 | V11: breakout_or_reverse | W11: 45751.417
A12: A | B12: 3 | C12: 45751 | D12: 45751.667 | E12: 45751.667 | F12: EXIT | G12: BUY | H12: -1 | I12: 194 | J12: 502.3976 | K12: 537.23451 | L12: 516.47255 | M12: 0.0067392367 | N12: 509.55478 | O12: 537.23451 | P12: 509.55478 | Q12: 1 | R12: 2095.8014 | S12: 0.679 | T12: 0.194 | U12: 2094.9284 | V12: session_close | W12: 45751.646
A13: A | B13: 4 | C13: 45754 | D13: 45754.583 | E13: 45754.583 | F13: ENTRY | G13: BUY | H13: 1 | I13: 210 | J13: 506.3052 | K13: 505.09718 | L13: 489.97167 | M13: 0.0053735858 | N13: 496.59524 | O13: 505.09718 | P13: 489.97167 | Q13: 1 | R13: 0 | S13: 0.735 | T13: 0.21 | U13: -0.945 | V13: breakout_or_reverse | W13: 45754.562
A14: A | B14: 4 | C14: 45754 | D14: 45754.667 | E14: 45754.667 | F14: EXIT | G14: SELL | H14: 1 | I14: 210 | J14: 501.5028 | K14: 506.88636 | L14: 488.21731 | M14: 0.0089348792 | N14: 497.44856 | O14: 506.88636 | P14: 488.21731 | Q14: 1 | R14: -1008.504 | S14: 0.735 | T14: 0.21 | U14: -1009.449 | V14: session_close | W14: 45754.646
A15: A | B15: 5 | C15: 45755 | D15: 45755.646 | E15: 45755.646 | F15: ENTRY | G15: SELL | H15: -1 | I15: 197 | J15: 494.4271 | K15: 524.08277 | L15: 497.61978 | M15: 0.007742369 | N15: 507.39754 | O15: 524.08277 | P15: 497.61978 | Q15: 1 | R15: 0 | S15: 0.6895 | T15: 0.197 | U15: -0.8865 | V15: breakout_or_reverse | W15: 45755.625
A16: A | B16: 5 | C16: 45755 | D16: 45755.667 | E16: 45755.667 | F16: EXIT | G16: BUY | H16: -1 | I16: 197 | J16: 493.6479 | K16: 525.35521 | L16: 496.39274 | M16: 0.010189103 | N16: 504.2758 | O16: 525.35521 | P16: 496.39274 | Q16: 1 | R16: 153.5024 | S16: 0.6895 | T16: 0.197 | U16: 152.6159 | V16: session_close | W16: 45755.646
A17: A | B17: 6 | C17: 45756 | D17: 45756.458 | E17: 45756.458 | F17: ENTRY | G17: SELL | H17: -1 | I17: 206 | J17: 490.317 | K17: 500.56818 | L17: 490.44998 | M17: 0.0064775257 | N17: 495.30708 | O17: 500.56818 | P17: 490.44998 | Q17: 1 | R17: 0 | S17: 0.721 | T17: 0.206 | U17: -0.927 | V17: breakout_or_reverse | W17: 45756.438
A18: A | B18: 6 | C18: 45756 | D18: 45756.562 | E18: 45756.562 | F18: EXIT | G18: BUY | H18: -1 | I18: 206 | J18: 521.7765 | K18: 502.47451 | L18: 488.55783 | M18: 0.010310534 | N18: 506.47917 | O18: 506.47917 | P18: 488.55783 | Q18: 1 | R18: -6480.657 | S18: 0.721 | T18: 0.206 | U18: -6481.584 | V18: breakout_or_reverse | W18: 45756.542
... A736: C | B736: 135 | C736: 45992 | D736: 45992.458 | E736: 45992.458 | F736: EXIT | G736: BUY | H736: -1 | I736: 317 | J736: 681.73 | K736: 685.48424 | L736: 679.4614 | M736: 0.0030644851 | N736: 681.04455 | O736: 685.48424 | P736: 679.4614 | Q736: 1.9377462 | R736: -651.435 | S736: 1.1095 | T736: 0.317 | U736: -652.8615 | V736: stop_or_reverse | W736: 45992.438

Sheet Signal Inputs
A2: Intraday signal and VWAP build | all sessions
A3: Prepared rows from the unchanged baseline. Time = inferred availability, source label = original workbook timestamp.
A6: Source label | B6: Available at | C6: Date | D6: Observed price $ | E6: Source volume | F6: Interval volume | G6: Cumulative volume | H6: Open proxy $ | I6: Prior close $ | J6: Noise count | K6: Noise σ | L6: Upper $ | M6: Lower $ | N6: VWAP proxy $ | O6: Long stop $ | P6: Short stop $ | Q6: Eligible | R6: At close | S6: Scheduled close | T6: Source AV row
A7: 45729.396 | B7: 45729.417 | C7: 45729 | D7: 549.9453 | E7: 3376733 | F7: 3376733 | G7: 3376733 | H7: 549.9453 | I7: 554.0158 | J7: 0 | N7: 549.9453 | Q7: 0 | R7: 0 | S7: 45729.667 | T7: 2545
A8: 45729.417 | B8: 45729.438 | C8: 45729 | D8: 552.3206 | E8: 3104572 | F8: 3104572 | G8: 6481305 | H8: 549.9453 | I8: 554.0158 | J8: 0 | N8: 551.08308 | Q8: 0 | R8: 0 | S8: 45729.667 | T8: 2544
A9: 45729.438 | B9: 45729.458 | C9: 45729 | D9: 551.2501 | E9: 2113298 | F9: 2113298 | G9: 8594603 | H9: 549.9453 | I9: 554.0158 | J9: 0 | N9: 551.12415 | Q9: 0 | R9: 0 | S9: 45729.667 | T9: 2543
A10: 45729.458 | B10: 45729.479 | C10: 45729 | D10: 549.4259 | E10: 1985860 | F10: 1985860 | G10: 10580463 | H10: 549.9453 | I10: 554.0158 | J10: 0 | N10: 550.8054 | Q10: 0 | R10: 0 | S10: 45729.667 | T10: 2542
A11: 45729.479 | B11: 45729.5 | C11: 45729 | D11: 547.7606 | E11: 3384171 | F11: 3384171 | G11: 13964634 | H11: 549.9453 | I11: 554.0158 | J11: 0 | N11: 550.06753 | Q11: 0 | R11: 0 | S11: 45729.667 | T11: 2541
A12: 45729.5 | B12: 45729.521 | C12: 45729 | D12: 547.7407 | E12: 2046320 | F12: 2046320 | G12: 16010954 | H12: 549.9453 | I12: 554.0158 | J12: 0 | N12: 549.77014 | Q12: 0 | R12: 0 | S12: 45729.667 | T12: 2540
A13: 45729.521 | B13: 45729.542 | C13: 45729 | D13: 547.7903 | E13: 3163341 | F13: 3163341 | G13: 19174295 | H13: 549.9453 | I13: 554.0158 | J13: 0 | N13: 549.44351 | Q13: 0 | R13: 0 | S13: 45729.667 | T13: 2539
A14: 45729.542 | B14: 45729.562 | C14: 45729 | D14: 546.2241 | E14: 2542120 | F14: 2542120 | G14: 21716415 | H14: 549.9453 | I14: 554.0158 | J14: 0 | N14: 549.06665 | Q14: 0 | R14: 0 | S14: 45729.667 | T14: 2538
A15: 45729.562 | B15: 45729.583 | C15: 45729 | D15: 545.2228 | E15: 2811644 | F15: 2811644 | G15: 24528059 | H15: 549.9453 | I15: 554.0158 | J15: 0 | N15: 548.62603 | Q15: 0 | R15: 0 | S15: 45729.667 | T15: 2537
A16: 45729.583 | B16: 45729.604 | C16: 45729 | D16: 548.2857 | E16: 2882136 | F16: 2882136 | G16: 27410195 | H16: 549.9453 | I16: 554.0158 | J16: 0 | N16: 548.59024 | Q16: 0 | R16: 0 | S16: 45729.667 | T16: 2536
A17: 45729.604 | B17: 45729.625 | C17: 45729 | D17: 548.9898 | E17: 2802139 | F17: 2802139 | G17: 30212334 | H17: 549.9453 | I17: 554.0158 | J17: 0 | N17: 548.6273 | Q17: 0 | R17: 0 | S17: 45729.667 | T17: 2535
A18: 45729.625 | B18: 45729.646 | C18: 45729 | D18: 546.6899 | E18: 2909677 | F18: 2909677 | G18: 33122011 | H18: 549.9453 | I18: 554.0158 | J18: 0 | N18: 548.45711 | Q18: 0 | R18: 0 | S18: 45729.667 | T18: 2534
... A188: 45748.646 | B188: 45748.667 | C188: 45748 | D188: 557.77 | E188: 6894220 | F188: 6894220 | G188: 36367822 | H188: 554.0215 | I188: 556.1988 | J188: 13 | N188: 555.92333 | Q188: 0 | R188: 1 | S188: 45748.667 | T188: 2351
A189: 45749.396 | B189: 45749.417 | C189: 45749 | D189: 555.3837 | E189: 4255808 | F189: 4255808 | G189: 4255808 | H189: 555.3837 | I189: 557.7698 | J189: 14 | K189: 0 | L189: 557.7698 | M189: 555.3837 | N189: 555.3837 | O189: 557.7698 | P189: 555.3837 | Q189: 1 | R189: 0 | S189: 45749.667 | T189: 2349
A190: 45749.417 | B190: 45749.438 | C190: 45749 | D190: 557.6407 | E190: 2212118 | F190: 2212118 | G190: 6467926 | H190: 555.3837 | I190: 557.7698 | J190: 14 | K190: 0.0020205715 | L190: 558.89681 | M190: 554.26151 | N190: 556.15562 | O190: 558.89681 | P190: 554.26151 | Q190: 1 | R190: 0 | S190: 45749.667 | T190: 2348
A191: 45749.438 | B191: 45749.458 | C191: 45749 | D191: 558.8339 | E191: 1872016 | F191: 1872016 | G191: 8339942 | H191: 555.3837 | I191: 557.7698 | J191: 14 | K191: 0.0031677259 | L191: 559.53666 | M191: 553.6244 | N191: 556.7568 | O191: 559.53666 | P191: 553.6244 | Q191: 1 | R191: 0 | S191: 45749.667 | T191: 2347
A192: 45749.458 | B192: 45749.479 | C192: 45749 | D192: 560.0867 | E192: 2113683 | F192: 2113683 | G192: 10453625 | H192: 555.3837 | I192: 557.7698 | J192: 14 | K192: 0.0031892078 | L192: 559.54864 | M192: 553.61247 | N192: 557.43009 | O192: 559.54864 | P192: 553.61247 | Q192: 1 | R192: 0 | S192: 45749.667 | T192: 2346
A193: 45749.479 | B193: 45749.5 | C193: 45749 | D193: 559.1322 | E193: 2235742 | F193: 2235742 | G193: 12689367 | H193: 555.3837 | I193: 557.7698 | J193: 14 | K193: 0.0040052144 | L193: 560.00379 | M193: 553.15927 | N193: 557.72999 | O193: 560.00379 | P193: 553.15927 | Q193: 1 | R193: 0 | S193: 45749.667 | T193: 2345
A194: 45749.5 | B194: 45749.521 | C194: 45749 | D194: 561.1009 | E194: 1594847 | F194: 1594847 | G194: 14284214 | H194: 555.3837 | I194: 557.7698 | J194: 14 | K194: 0.0038691255 | L194: 559.92788 | M194: 553.23485 | N194: 558.10635 | O194: 559.92788 | P194: 553.23485 | Q194: 1 | R194: 0 | S194: 45749.667 | T194: 2344
A195: 45749.521 | B195: 45749.542 | C195: 45749 | D195: 562.4581 | E195: 2547514 | F195: 2547514 | G195: 16831728 | H195: 555.3837 | I195: 557.7698 | J195: 14 | K195: 0.0042296214 | L195: 560.12896 | M195: 553.03464 | N195: 558.765 | O195: 560.12896 | P195: 553.03464 | Q195: 1 | R195: 0 | S195: 45749.667 | T195: 2343
A196: 45749.542 | B196: 45749.562 | C196: 45749 | D196: 562.7912 | E196: 2593586 | F196: 2593586 | G196: 19425314 | H196: 555.3837 | I196: 557.7698 | J196: 14 | K196: 0.0043798119 | L196: 560.21273 | M196: 552.95122 | N196: 559.30256 | O196: 560.21273 | P196: 552.95122 | Q196: 1 | R196: 0 | S196: 45749.667 | T196: 2342
A197: 45749.562 | B197: 45749.583 | C197: 45749 | D197: 560.6435 | E197: 2667686 | F197: 2667686 | G197: 22093000 | H197: 555.3837 | I197: 557.7698 | J197: 14 | K197: 0.0045881756 | L197: 560.32895 | M197: 552.8355 | N197: 559.46448 | O197: 560.32895 | P197: 552.8355 | Q197: 1 | R197: 0 | S197: 45749.667 | T197: 2341
A198: 45749.583 | B198: 45749.604 | C198: 45749 | D198: 557.7998 | E198: 2223449 | F198: 2223449 | G198: 24316449 | H198: 555.3837 | I198: 557.7698 | J198: 14 | K198: 0.0043827008 | L198: 560.21434 | M198: 552.94962 | N198: 559.31226 | O198: 560.21434 | P198: 552.94962 | Q198: 1 | R198: 0 | S198: 45749.667 | T198: 2340
A199: 45749.604 | B199: 45749.625 | C199: 45749 | D199: 558.118 | E199: 2388119 | F199: 2388119 | G199: 26704568 | H199: 555.3837 | I199: 557.7698 | J199: 14 | K199: 0.0052780675 | L199: 560.71375 | M199: 552.45235 | N199: 559.20546 | O199: 560.71375 | P199: 552.45235 | Q199: 1 | R199: 0 | S199: 45749.667 | T199: 2339
A200: 45749.625 | B200: 45749.646 | C200: 45749 | D200: 559.689 | E200: 1869869 | F200: 1869869 | G200: 28574437 | H200: 555.3837 | I200: 557.7698 | J200: 14 | K200: 0.0056137156 | L200: 560.90096 | M200: 552.26593 | N200: 559.2371 | O200: 560.90096 | P200: 552.26593 | Q200: 1 | R200: 0 | S200: 45749.667 | T200: 2338
... A2360: 45992.646 | B2360: 45992.667 | C2360: 45992 | D2360: 680.27 | E2360: 12550585 | F2360: 12550585 | G2360: 44388716 | H2360: 681.55 | I2360: 683.39 | J2360: 13 | K2360: 0.0076990438 | L2360: 688.65145 | M2360: 676.30272 | N2360: 680.91971 | O2360: 688.65145 | P2360: 676.30272 | Q2360: 1 | R2360: 1 | S2360: 45992.667 | T2360: 3

Sheet April Noise
A2: April 2 at 11:30 | 14 prior time-of-day observations
A3: Source cell addresses refer to the original AV.Clean sheet; source rows are copied into Source AV Clean.
A6: Target day | B6: Slot | C6: Historical day | D6: Open proxy $ | E6: Slot price $ | F6: Absolute move | G6: Open source cell | H6: Price source cell | I6: Source label | J6: Available at
A7: 45749 | B7: 11:30 | C7: 45729 | D7: 549.9453 | E7: 549.4259 | F7: =ABS(E7/D7-1) -> 0.00094445757 | G7: AV.Clean!B2545 | H7: AV.Clean!B2542 | I7: 45729.458 | J7: 45729.479
A8: 45749 | B8: 11:30 | C8: 45730 | D8: 552.0728 | E8: 556.2068 | F8: =ABS(E8/D8-1) -> 0.0074881429 | G8: AV.Clean!B2531 | H8: AV.Clean!B2528 | I8: 45730.458 | J8: 45730.479
A9: 45749 | B9: 11:30 | C9: 45733 | D9: 560.5039 | E9: 559.1558 | F9: =ABS(E9/D9-1) -> 0.0024051572 | G9: AV.Clean!B2517 | H9: AV.Clean!B2514 | I9: 45733.458 | J9: 45733.479
A10: 45749 | B10: 11:30 | C10: 45734 | D10: 555.8831 | E10: 554.9972 | F10: =ABS(E10/D10-1) -> 0.0015936804 | G10: AV.Clean!B2503 | H10: AV.Clean!B2500 | I10: 45734.458 | J10: 45734.479
A11: 45749 | B11: 11:30 | C11: 45735 | D11: 559.2103 | E11: 559.696 | F11: =ABS(E11/D11-1) -> 0.00086854623 | G11: AV.Clean!B2489 | H11: AV.Clean!B2486 | I11: 45735.458 | J11: 45735.479
A12: 45749 | B12: 11:30 | C12: 45736 | D12: 561.6885 | E12: 563.9686 | F12: =ABS(E12/D12-1) -> 0.0040593674 | G12: AV.Clean!B2475 | H12: AV.Clean!B2472 | I12: 45736.458 | J12: 45736.479
A13: 45749 | B13: 11:30 | C13: 45737 | D13: 556.7365 | E13: 556.6166 | F13: =ABS(E13/D13-1) -> 0.0002153622 | G13: AV.Clean!B2461 | H13: AV.Clean!B2458 | I13: 45737.458 | J13: 45737.479
A14: 45749 | B14: 11:30 | C14: 45740 | D14: 569.5275 | E14: 570.4671 | F14: =ABS(E14/D14-1) -> 0.0016497886 | G14: AV.Clean!B2447 | H14: AV.Clean!B2444 | I14: 45740.458 | J14: 45740.479
A15: 45749 | B15: 11:30 | C15: 45741 | D15: 571.4266 | E15: 572.416 | F15: =ABS(E15/D15-1) -> 0.001731456 | G15: AV.Clean!B2433 | H15: AV.Clean!B2430 | I15: 45741.458 | J15: 45741.479
A16: 45749 | B16: 11:30 | C16: 45742 | D16: 570.2513 | E16: 569.0453 | F16: =ABS(E16/D16-1) -> 0.0021148571 | G16: AV.Clean!B2419 | H16: AV.Clean!B2416 | I16: 45742.458 | J16: 45742.479
A17: 45749 | B17: 11:30 | C17: 45743 | D17: 565.093 | E17: 566.6192 | F17: =ABS(E17/D17-1) -> 0.0027007944 | G17: AV.Clean!B2405 | H17: AV.Clean!B2402 | I17: 45743.458 | J17: 45743.479
A18: 45749 | B18: 11:30 | C18: 45744 | D18: 559.8779 | E18: 555.7018 | F18: =ABS(E18/D18-1) -> 0.0074589477 | G18: AV.Clean!B2391 | H18: AV.Clean!B2388 | I18: 45744.458 | J18: 45744.479
... A20: 45749 | B20: 11:30 | C20: 45748 | D20: 554.0215 | E20: 557.5811 | F20: =ABS(E20/D20-1) -> 0.0064250214 | G20: AV.Clean!B2363 | H20: AV.Clean!B2360 | I20: 45748.458 | J20: 45748.479
D22: Mean Noise σ | E22: =AVERAGE(F7:F20) -> 0.0031892078
D23: April 2 open proxy | E23: 555.3837
D24: Prior close | E24: 557.7698
D25: Upper boundary | E25: =MAX(E23,E24)*(1+E22) -> 559.54864
D26: Lower boundary | E26: =MIN(E23,E24)*(1-E22) -> 553.61247
D27: Observed 11:30 price | E27: 560.0867
D28: Long signal (1=yes) | E28: =IF(E27>E25,1,0) -> 1

Sheet April Volatility
A2: April 2 | 14 lagged daily SPY returns and sizing
A3: Sample standard deviation uses denominator 13. Input close cells refer to the original BBRG.Daily sheet.
A6: Target day | B6: Return day | C6: Prior day | D6: Prior close $ | E6: Close $ | F6: Daily return | G6: Prior source cell | H6: Close source cell
A7: 45749 | B7: 45729 | C7: 45728 | D7: 554.0158 | E7: 546.6305 | F7: =E7/D7-1 -> -0.013330486 | G7: BBRG.Daily!C184 | H7: BBRG.Daily!C183
A8: 45749 | B8: 45730 | C8: 45729 | D8: 546.6305 | E8: 557.9216 | F8: =E8/D8-1 -> 0.020655818 | G8: BBRG.Daily!C183 | H8: BBRG.Daily!C182
A9: 45749 | B9: 45733 | C9: 45730 | D9: 557.9216 | E9: 562.2239 | F9: =E9/D9-1 -> 0.0077112985 | G9: BBRG.Daily!C182 | H9: BBRG.Daily!C181
A10: 45749 | B10: 45734 | C10: 45733 | D10: 562.2239 | E10: 556.1471 | F10: =E10/D10-1 -> -0.010808505 | G10: BBRG.Daily!C181 | H10: BBRG.Daily!C180
A11: 45749 | B11: 45735 | C11: 45734 | D11: 556.1471 | E11: 562.204 | F11: =E11/D11-1 -> 0.010890824 | G11: BBRG.Daily!C180 | H11: BBRG.Daily!C179
A12: 45749 | B12: 45736 | C12: 45735 | D12: 562.204 | E12: 560.5783 | F12: =E12/D12-1 -> -0.002891655 | G12: BBRG.Daily!C179 | H12: BBRG.Daily!C178
A13: 45749 | B13: 45737 | C13: 45736 | D13: 560.5783 | E13: 560.7626 | F13: =E13/D13-1 -> 0.00032876763 | G13: BBRG.Daily!C178 | H13: BBRG.Daily!C177
A14: 45749 | B14: 45740 | C14: 45737 | D14: 560.7626 | E14: 570.8049 | F14: =E14/D14-1 -> 0.017908291 | G14: BBRG.Daily!C177 | H14: BBRG.Daily!C176
A15: 45749 | B15: 45741 | C15: 45740 | D15: 570.8049 | E15: 572.1771 | F15: =E15/D15-1 -> 0.0024039738 | G15: BBRG.Daily!C176 | H15: BBRG.Daily!C175
A16: 45749 | B16: 45742 | C16: 45741 | D16: 572.1771 | E16: 565.3463 | F16: =E16/D16-1 -> -0.011938262 | G16: BBRG.Daily!C175 | H16: BBRG.Daily!C174
A17: 45749 | B17: 45743 | C17: 45742 | D17: 565.3463 | E17: 563.8449 | F17: =E17/D17-1 -> -0.0026557174 | G17: BBRG.Daily!C174 | H17: BBRG.Daily!C173
A18: 45749 | B18: 45744 | C18: 45743 | D18: 563.8449 | E18: 552.4901 | F18: =E18/D18-1 -> -0.020138162 | G18: BBRG.Daily!C173 | H18: BBRG.Daily!C172
... A20: 45749 | B20: 45748 | C20: 45747 | D20: 556.1988 | E20: 557.7698 | F20: =E20/D20-1 -> 0.0028245296 | G20: BBRG.Daily!C171 | H20: BBRG.Daily!C170
D22: Mean return | E22: =AVERAGE(F7:F20) -> 0.000548101
D23: Daily SPY volatility | E23: =_xlfn.STDEV.S(F7:F20) -> 0.011891081
D24: Target volatility | E24: ='Method Notes'!B6 -> 0.02
D25: Leverage cap | E25: ='Method Notes'!B7 -> 4
D26: Model C leverage | E26: =MIN(E25,E24/E23) -> 1.6819329
D27: Start equity $ | E27: ='Method Notes'!B5 -> 100000
D28: Open proxy $ | E28: ='April Noise'!E23 -> 555.3837
D29: Shares | E29: =INT(E27*E26/E28) -> 302

Sheet Sensitivity
A2: Implementation ambiguity | one change at a time
A3: Fixed independent-run outputs. Baseline cases preserve original assumptions; changed trade count excludes quantity-only changes.
A6: Case | B6: Model | C6: Cumulative return | D6: Annual volatility | E6: Sharpe | F6: Max drawdown | G6: Round trips | H6: Total costs $ | I6: Baseline trades changed | J6: Quantity-only changes
A7: baseline_replay | B7: A | C7: 0.035942128 | D7: 0.06649385 | E7: 0.82962629 | F7: -0.05059485 | G7: 95 | H7: 138.33 | I7: 0 | J7: 0
A8: baseline_replay | B8: B | C8: 0.04474041 | D8: 0.072406091 | E8: 0.94237324 | F8: -0.028361244 | G8: 135 | H8: 201.42 | I8: 0 | J8: 0
A9: baseline_replay | B9: C | C9: 0.11139267 | D9: 0.15499541 | E9: 1.096886 | F9: -0.04816985 | G9: 135 | H9: 534.915 | I9: 0 | J9: 0
A10: midpoint_vwap | B10: A | C10: 0.035942128 | D10: 0.06649385 | E10: 0.82962629 | F10: -0.05059485 | G10: 95 | H10: 138.33 | I10: 0 | J10: 0
A11: midpoint_vwap | B11: B | C11: 0.04474041 | D11: 0.072406091 | E11: 0.94237324 | F11: -0.028361244 | G11: 135 | H11: 201.42 | I11: 0 | J11: 0
A12: midpoint_vwap | B12: C | C12: 0.11139267 | D12: 0.15499541 | E12: 1.096886 | F12: -0.04816985 | G12: 135 | H12: 534.915 | I12: 0 | J12: 0
A13: delay_30m | B13: A | C13: -0.031750348 | D13: 0.082488974 | E13: -0.5449768 | F13: -0.086253368 | G13: 89 | H13: 123.615 | I13: 95 | J13: 0
A14: delay_30m | B14: B | C14: 0.012134245 | D14: 0.066119544 | E14: 0.30628376 | F14: -0.039744441 | G14: 121 | H14: 176.31 | I14: 135 | J14: 0
A15: delay_30m | B15: C | C15: 0.039019362 | D15: 0.11747127 | E15: 0.54639422 | F15: -0.05499875 | G15: 121 | H15: 459.234 | I15: 135 | J15: 0
A16: vwap_entry_gate | B16: A | C16: 0.035942128 | D16: 0.06649385 | E16: 0.82962629 | F16: -0.05059485 | G16: 95 | H16: 138.33 | I16: 0 | J16: 0
A17: vwap_entry_gate | B17: B | C17: 0.04474041 | D17: 0.072406091 | E17: 0.94237324 | F17: -0.028361244 | G17: 135 | H17: 201.42 | I17: 0 | J17: 0
A18: vwap_entry_gate | B18: C | C18: 0.11139267 | D18: 0.15499541 | E18: 1.096886 | F18: -0.04816985 | G18: 135 | H18: 534.915 | I18: 0 | J18: 0
... A24: higher_costs | B24: C | C24: 0.10807336 | D24: 0.15494397 | E24: 1.0682347 | F24: -0.048668211 | G24: 135 | H24: 830.872 | I24: 0 | J24: 75

Sheet Concentration
A2: Model C | best/worst day dependence
A3: Removal sets selected daily net returns to zero without rerunning the strategy; rankings are hindsight diagnostics.
A6: Tail | B6: Days removed | C6: Selected dates | D6: Selected net P&L $ | E6: Share of total profit | F6: Return without | G6: Change vs baseline | H6: Selected compounded return
A7: best | B7: 1 | C7: 2025-10-10 | D7: 9480.384 | E7: 0.8510779 | F7: 0.016622967 | G7: 0.094769703 | H7: 0.093220109
A8: best | B8: 3 | C8: 2025-10-10; 2025-04-09; 2025-11-20 | D8: 15760.743 | E8: 1.4148815 | F8: -0.041857445 | G8: 0.15325011 | H8: 0.159945
A9: best | B9: 5 | C9: 2025-10-10; 2025-04-09; 2025-11-20; 2025-04-04; 2025-11-13 | D9: 19903.235 | E9: 1.7867634 | F9: -0.079515909 | G9: 0.19090858 | H9: 0.20740019
A10: worst | B10: 1 | C10: 2025-11-21 | D10: -2255.904 | E10: -0.20251817 | F10: 0.13420724 | G10: -0.02281457 | H10: -0.020114992
A11: worst | B11: 3 | C11: 2025-11-21; 2025-09-17; 2025-09-18 | D11: -5829.4698 | E11: -0.52332616 | F11: 0.17424659 | G11: -0.062853916 | H11: -0.053527017
A12: worst | B12: 5 | C12: 2025-11-21; 2025-09-17; 2025-09-18; 2025-10-03; 2025-04-02 | D12: -8720.942 | E12: -0.78290089 | F12: 0.20833765 | G12: -0.09694498 | H12: -0.080230041
A16: Selected day ranking
A18: Tail | B18: Rank | C18: Date | D18: Daily return | E18: Net P&L $ | F18: Start equity $ | G18: Share of total profit
A19: best | B19: 1 | C19: 45940 | D19: 0.093220109 | E19: 9480.384 | F19: 101698.92 | G19: 0.8510779
A20: best | B20: 2 | C20: 45756 | D20: 0.034974379 | E20: 3525.7572 | F20: 100809.72 | G20: 0.31651609
A21: best | B21: 3 | C21: 45981 | D21: 0.025180149 | E21: 2754.602 | F21: 109395.78 | G21: 0.24728755
A22: best | B22: 4 | C22: 45751 | D22: 0.02497847 | E22: 2471.8489 | F22: 98959.181 | G22: 0.22190409
A23: best | B23: 5 | C23: 45974 | D23: 0.01554483 | E23: 1670.643 | F23: 107472.58 | G23: 0.14997782
A24: worst | B24: 1 | C24: 45982 | D24: -0.020114992 | E24: -2255.904 | F24: 112150.38 | G24: -0.20251817
A25: worst | B25: 2 | C25: 45917 | D25: -0.017813592 | E25: -1866.9196 | F25: 104803.09 | G25: -0.16759807
A26: worst | B26: 3 | C26: 45918 | D26: -0.016579654 | E26: -1706.6462 | F26: 102936.17 | G26: -0.15320992
A27: worst | B27: 4 | C27: 45933 | D27: -0.015507059 | E27: -1600.845 | F27: 103233.31 | G27: -0.14371188
A28: worst | B28: 5 | C28: 45749 | D28: -0.012906272 | E28: -1290.6272 | F28: 100000 | G28: -0.11586285

Sheet Source AV Clean
A2: Supplied workbook | AV.Clean
A3: Unmodified values and original Excel row numbers. Descending date order matches the source sheet.
A6: Original row | B6: Time Stamp | C6: Last Price $ | D6: Volume, AV
A7: 2 | B7: 45992.667 | C7: 680.27 | D7: 16747236
A8: 3 | B8: 45992.646 | C8: 680.27 | D8: 12550585
A9: 4 | B9: 45992.625 | C9: 680.765 | D9: 2548565
A10: 5 | B10: 45992.604 | C10: 680.14 | D10: 3033602
A11: 6 | B11: 45992.583 | C11: 680.49 | D11: 3145771
A12: 7 | B12: 45992.562 | C12: 682.815 | D12: 1582845
A13: 8 | B13: 45992.542 | C13: 682.49 | D13: 1345902
A14: 9 | B14: 45992.521 | C14: 682.005 | D14: 1374588
A15: 10 | B15: 45992.5 | C15: 682.01 | D15: 1516606
A16: 11 | B16: 45992.479 | C16: 681.93 | D16: 1954095
A17: 12 | B17: 45992.458 | C17: 681.11 | D17: 1802813
A18: 13 | B18: 45992.438 | C18: 681.73 | D18: 3181322
... A2550: 2545 | B2550: 45729.396 | C2550: 549.9453 | D2550: 3376733

Sheet Source BBRG Daily
A2: Supplied workbook | BBRG.Daily
A3: Unmodified daily close and volume values. Original Excel row numbers allow direct comparison with attached dataset.
A6: Original row | B6: Time Stamp | C6: Last Price $ | D6: Volume | E6: SMAVG (15)
A7: 2 | B7: 45992 | C7: 680.27 | D7: 61135952 | E7: 88668808
A8: 3 | B8: 45989 | C8: 683.39 | D8: 49212032 | E8: 91299240
A9: 4 | B9: 45987 | C9: 679.68 | D9: 71879600 | E9: 93687456
A10: 5 | B10: 45986 | C10: 675.02 | D10: 81077088 | E10: 93855640
A11: 6 | B11: 45985 | C11: 668.73 | D11: 80437936 | E11: 93678968
A12: 7 | B12: 45982 | C12: 659.03 | D12: 123956200 | E12: 92137440
A13: 8 | B13: 45981 | C13: 652.53 | D13: 165293520 | E13: 89684632
A14: 9 | B14: 45980 | C14: 662.63 | D14: 94702952 | E14: 83754112
A15: 10 | B15: 45979 | C15: 660.08 | D15: 114467488 | E15: 83131400
A16: 11 | B16: 45978 | C16: 665.67 | D16: 90456104 | E16: 79616104
A17: 12 | B17: 45975 | C17: 671.93 | D17: 96846672 | E17: 77808352
A18: 13 | B18: 45974 | C18: 672.04 | D18: 103457792 | E18: 76309008
... A189: 184 | B189: 45728 | C189: 554.0158 | D189: 69588168 | E189: 73449224
A190: 185 | B190: 45727 | C190: 551.0914 | D190: 88102112
A191: 186 | B191: 45726 | C191: 555.7109 | D191: 99326624
A192: 187 | B192: 45723 | C192: 570.9177 | D192: 81158816
A193: 188 | B193: 45722 | C193: 567.7356 | D193: 80094864
A194: 189 | B194: 45721 | C194: 577.9957 | D194: 71230528
A195: 190 | B195: 45720 | C195: 571.8495 | D195: 109648208
A196: 191 | B196: 45719 | C196: 578.6995 | D196: 74249200
A197: 192 | B197: 45716 | C197: 589.0191 | D197: 88744104
A198: 193 | B198: 45715 | C198: 579.9684 | D198: 74196664
A199: 194 | B199: 45714 | C199: 589.376 | D199: 43321576
A200: 195 | B200: 45713 | C200: 589.0786 | D200: 58266472
A201: 196 | B201: 45712 | C201: 592.0228 | D201: 50737212
... A203: 198 | B203: 45708 | C203: 605.0784 | D203: 36554000

Sheet Source BBRG Intraday
A2: Supplied workbook | BBRG.Intraday
A3: Original intraday values kept for source comparison; AV.Clean is the baseline source after volume cleaning.
A6: Original row | B6: Time Stamp | C6: Last Price $ | D6: Volume | E6: SMAVG (15)
A7: 2 | B7: 45992.667 | C7: 680.27 | D7: 0 | E7: 2959247.8
A8: 3 | B8: 45992.646 | C8: 680.27 | D8: 12550585 | E8: 2959247.8
A9: 4 | B9: 45992.625 | C9: 680.765 | D9: 2548565 | E9: 2122542
A10: 5 | B10: 45992.604 | C10: 680.14 | D10: 3033602 | E10: 1952637.8
A11: 6 | B11: 45992.583 | C11: 680.49 | D11: 3145771 | E11: 2441319.8
A12: 7 | B12: 45992.562 | C12: 682.815 | D12: 1582845 | E12: 2453621
A13: 8 | B13: 45992.542 | C13: 682.49 | D13: 1345902 | E13: 2578816.2
A14: 9 | B14: 45992.521 | C14: 682.005 | D14: 1374588 | E14: 2719327.2
A15: 10 | B15: 45992.5 | C15: 682.01 | D15: 1516606 | E15: 2844391.2
A16: 11 | B16: 45992.479 | C16: 681.93 | D16: 1954095 | E16: 2983451
A17: 12 | B17: 45992.458 | C17: 681.11 | D17: 1802813 | E17: 3144017
A18: 13 | B18: 45992.438 | C18: 681.73 | D18: 3181322 | E18: 3023829.5
... A2534: 2529 | B2534: 45730.396 | C2534: 552.0728 | D2534: 4982233 | E2534: 3273701.2
A2535: 2530 | B2535: 45729.667 | C2535: 546.6305 | D2535: 0
A2536: 2531 | B2536: 45729.646 | C2536: 546.6305 | D2536: 11001275
A2537: 2532 | B2537: 45729.625 | C2537: 546.6899 | D2537: 2909677
A2538: 2533 | B2538: 45729.604 | C2538: 548.9898 | D2538: 2802139
A2539: 2534 | B2539: 45729.583 | C2539: 548.2857 | D2539: 2882136
A2540: 2535 | B2540: 45729.562 | C2540: 545.2228 | D2540: 2811644
A2541: 2536 | B2541: 45729.542 | C2541: 546.2241 | D2541: 2542120
A2542: 2537 | B2542: 45729.521 | C2542: 547.7903 | D2542: 3163341
A2543: 2538 | B2543: 45729.5 | C2543: 547.7407 | D2543: 2046320
A2544: 2539 | B2544: 45729.479 | C2544: 547.7606 | D2544: 3384171
A2545: 2540 | B2545: 45729.458 | C2545: 549.4259 | D2545: 1985860
A2546: 2541 | B2546: 45729.438 | C2546: 551.2501 | D2546: 2113298
... A2548: 2543 | B2548: 45729.396 | C2548: 549.9453 | D2548: 3376733

Sheet Method Notes
A2: Method, fixed inputs, and workbook scope
A3: This workbook packages the finished Python backtest; editing source data does not rerun the full trade-state machine.
D4: Live formula parameters
A5: Initial equity $ | B5: 100000
A6: Target daily volatility | B6: 0.02
A7: Leverage cap | B7: 4
A8: Commission/share $ | B8: 0.0035
A9: Slippage/share $ | B9: 0.001
A11: Parameter / issue | B11: Value or interpretation
A12: Noise lookback sessions | B12: 14
A13: Commission per share per execution | B13: 0.0035
A14: Slippage per share per execution | B14: 0.001
A15: Trading days per year | B15: 252
A16: First scored date | B16: 2025-04-02
A17: Last scored date | B17: 2025-12-01
A18: Open proxy | B18: First available half-hour observation; true 9:30 opening transaction unavailable.
A19: VWAP proxy | B19: Cumulative sum of observed interval-end price × interval volume / cumulative observed interval volume.
A20: Timestamp convention | B20: Inferred start-labeled source intervals. First interval becomes available at 10:00.
A21: Noise Area | B21: Mean of |historical time-slot price / historical open proxy - 1| over available prior 14 sessions.
A22: Upper / lower | B22: max(open proxy, previous close) × (1 + noise); min(open proxy, previous close) × (1 - noise).
A23: Model C shares | B23: floor(starting equity × min(4, 0.02 / prior-14-day sample SPY volatility) / open proxy).
A24: Early closes | B24: 2025-07-03 and 2025-11-28 force 13:00 close; later stale prints remain in raw source only.
A25: Trade costs | B25: 2 × shares × (commission + slippage) for a completed round trip.
A26: Annualization | B26: 252 sessions/year; zero risk-free rate.
A27: VWAP is approximate | B27: No transaction-level prices or complete interval dollar turnover are supplied.
... A31: Concentration | B31: Removing days is an attribution stress, not a modified executable trading strategy.
